baby/__init__.py
baby/augmentation.py
baby/brain.py
baby/brain_util.py
baby/crawler.py
baby/errors.py
baby/generator.py
baby/io.py
baby/layers.py
baby/losses.py
baby/models/I1_evolve_unet_4s_20200630.hdf5
baby/models/I1_evolve_unet_4s_20210302.hdf5
baby/models/I1_prime_unet_4s_20200630.hdf5
baby/models/I1_prime_unet_4s_20210302.hdf5
baby/models/I3_evolve_unet_4s_20200903.hdf5
baby/models/I3_evolve_unet_4s_20210215.hdf5
baby/models/I3_prime_unet_4s_20200903.hdf5
baby/models/I3_prime_unet_4s_20210215.hdf5
baby/models/I5_evolve_unet_4s_20210120.hdf5
baby/models/I5_prime_unet_4s_20210120.hdf5
baby/models/ct_GBC_20230511_10.pkl
baby/models/ct_GBC_20230511_11.pkl
baby/models/ct_GBC_20230511_15.pkl
baby/models/ct_GBC_20230511_5.pkl
baby/models/ct_GBC_20230511_6.pkl
baby/models/ct_GBC_20230511_7.pkl
baby/models/ct_GBC_20230511_8.pkl
baby/models/ct_HGBC_20230511_10.pkl
baby/models/ct_HGBC_20230511_11.pkl
baby/models/ct_HGBC_20230511_15.pkl
baby/models/ct_HGBC_20230511_5.pkl
baby/models/ct_HGBC_20230511_6.pkl
baby/models/ct_HGBC_20230511_7.pkl
baby/models/ct_HGBC_20230511_8.pkl
baby/models/ct_SVC_20230511_10.pkl
baby/models/ct_SVC_20230511_11.pkl
baby/models/ct_SVC_20230511_15.pkl
baby/models/ct_SVC_20230511_5.pkl
baby/models/ct_SVC_20230511_6.pkl
baby/models/ct_SVC_20230511_7.pkl
baby/models/ct_SVC_20230511_8.pkl
baby/models/ct_XGBC_20220703_10.pkl
baby/models/ct_XGBC_20220703_11.pkl
baby/models/ct_XGBC_20230511_10.pkl
baby/models/ct_XGBC_20230511_11.pkl
baby/models/ct_XGBC_20230511_15.pkl
baby/models/ct_XGBC_20230511_5.pkl
baby/models/ct_XGBC_20230511_6.pkl
baby/models/ct_XGBC_20230511_7.pkl
baby/models/ct_XGBC_20230511_8.pkl
baby/models/ct_rf_20230511_10.pkl
baby/models/ct_rf_20230511_11.pkl
baby/models/ct_rf_20230511_15.pkl
baby/models/ct_rf_20230511_5.pkl
baby/models/ct_rf_20230511_6.pkl
baby/models/ct_rf_20230511_7.pkl
baby/models/ct_rf_20230511_8.pkl
baby/models/flattener_60x_1z_evolve_20210302.json
baby/models/flattener_60x_1z_prime_20210302.json
aliby_baby-0.1.17.dist-info/WHEEL
aliby_baby-0.1.17.dist-info/LICENSE.txt
aliby_baby-0.1.17.dist-info/METADATA
aliby_baby-0.1.17.dist-info/RECORD
