Metadata-Version: 2.1
Name: aliby-baby
Version: 0.1.17
Summary: Birth Annotator for Budding Yeast
License: MIT
Author: Julian Pietsch
Author-email: jpietsch@ed.ac.uk
Requires-Python: >=3.7.1,<3.11
Classifier: License :: OSI Approved :: MIT License
Classifier: Programming Language :: Python :: 3
Classifier: Programming Language :: Python :: 3.8
Classifier: Programming Language :: Python :: 3.9
Classifier: Programming Language :: Python :: 3.10
Requires-Dist: Pillow (>=9.0.0,<10.0.0)
Requires-Dist: colorama (>=0.4.4,<0.5.0)
Requires-Dist: configspace (>=0.6.1,<0.7.0)
Requires-Dist: hpbandster (>=0.7.4,<0.8.0)
Requires-Dist: imageio (==2.8.0)
Requires-Dist: keras-tuner (==1.0.1)
Requires-Dist: matplotlib (>=3.5.1,<4.0.0)
Requires-Dist: numpy (==1.21.6)
Requires-Dist: pandas (==1.3.3)
Requires-Dist: protobuf (<=3.20.1)
Requires-Dist: ray (>=1.13.0,<2.0.0)
Requires-Dist: scikit-image (>=0.19.3,<0.20.0)
Requires-Dist: scikit-learn (>=1.0.2)
Requires-Dist: scikit-plot (>=0.3.7,<0.4.0)
Requires-Dist: tensorflow (>=2.0.0,<2.9.1)
Requires-Dist: tqdm (>=4.62.3,<5.0.0)
Requires-Dist: tune-sklearn (>=0.4.1,<0.5.0)
Requires-Dist: xgboost (==1.4.2)
